maxfuse/__init__.py
maxfuse/graph.py
maxfuse/match_utils.py
maxfuse/metrics.py
maxfuse/model.py
maxfuse/spatial_utils.py
maxfuse/utils.py
maxfuse-0.0.2.dist-info/METADATA
maxfuse-0.0.2.dist-info/WHEEL
maxfuse-0.0.2.dist-info/licenses/LICENSE
maxfuse-0.0.2.dist-info/RECORD
