Metadata-Version: 2.1
Name: maxfuse
Version: 0.0.2
Summary: Cross-modality matching of single cells via iterative fuzzy smoothed embedding
Project-URL: Homepage, https://github.com/shuxiaoc/maxfuse
Project-URL: Bug Tracker, https://github.com/shuxiaoc/maxfuse/issues
Author-email: Shuxiao Chen <shuxiaoc@gmail.com>, Bokai Zhu <bkzhu@stanford.edu>
License-File: LICENSE
Classifier: Operating System :: OS Independent
Classifier: Programming Language :: Python :: 3
Requires-Python: >=3.8
Requires-Dist: igraph
Requires-Dist: leidenalg
Requires-Dist: matplotlib
Requires-Dist: numpy
Requires-Dist: pandas
Requires-Dist: requests
Requires-Dist: scanpy
Requires-Dist: scikit-learn
Requires-Dist: scipy
